{
    "data": [
        {
            "avatar_url": "https://avatars.githubusercontent.com/u/69631?v=4",
            "id": "e0bcf3c7-a567-4189-84af-c5f6c1cb6b62",
            "name": "react-native",
            "description": "A framework for building native apps with React.",
            "language": "Javascript"
        },
        {
            "avatar_url": "https://avatars.githubusercontent.com/u/69631?v=4",
            "id": "8b106377-c823-4caf-80e3-b1ad342e7ddd",
            "name": "react-native",
            "description": "A framework for building native apps with React.",
            "language": "Javascript"
        },
        {
            "avatar_url": "https://avatars.githubusercontent.com/u/69631?v=4",
            "id": "06ac200f-bec5-4b90-9772-92ff8ab48544",
            "name": "react-native",
            "description": "A framework for building native apps with React.",
            "language": "Javascript"
        },
        {
            "avatar_url": "https://avatars.githubusercontent.com/u/69631?v=4",
            "id": "066f0baa-5c03-4297-bc76-425a89190d7c",
            "name": "react-native",
            "description": "A framework for building native apps with React.",
            "language": "Javascript"
        },
        {
            "avatar_url": "https://avatars.githubusercontent.com/u/69631?v=4",
            "id": "bcad92c5-8ee3-4ee0-a6b6-1d1e19f6bfe4",
            "name": "react-native",
            "description": "A framework for building native apps with React.",
            "language": "Javascript"
        }
    ]
}